uliweb/.DS_Store
uliweb/__init__.py
uliweb/__main__.py
uliweb/manage.py
uliweb/contrib/.DS_Store
uliweb/contrib/__init__.py
uliweb/contrib/eureka_app.zip
uliweb/contrib/auth/__init__.py
uliweb/contrib/auth/commands.py
uliweb/contrib/auth/config.ini
uliweb/contrib/auth/forms.py
uliweb/contrib/auth/info.ini
uliweb/contrib/auth/middle_auth.py
uliweb/contrib/auth/models.py
uliweb/contrib/auth/settings.ini
uliweb/contrib/auth/views.py
uliweb/contrib/auth/static/images/user20x20.jpg
uliweb/contrib/auth/static/images/user50x50.jpg
uliweb/contrib/auth/templates/login.html
uliweb/contrib/auth/templates/register.html
uliweb/contrib/cache/__init__.py
uliweb/contrib/cache/conf.py
uliweb/contrib/cache/info.ini
uliweb/contrib/cache/settings.ini
uliweb/contrib/clean/.DS_Store
uliweb/contrib/clean/__init__.py
uliweb/contrib/clean/commands.py
uliweb/contrib/clean/subcommands.py
uliweb/contrib/clean/static/readme.txt
uliweb/contrib/clean/templates/readme.txt
uliweb/contrib/csrf/__init__.py
uliweb/contrib/csrf/conf.py
uliweb/contrib/csrf/config.ini
uliweb/contrib/csrf/info.ini
uliweb/contrib/csrf/middleware.py
uliweb/contrib/csrf/settings.ini
uliweb/contrib/csrf/static/readme.txt
uliweb/contrib/csrf/templates/inc_jquery_csrf.html
uliweb/contrib/csrf/templates/readme.txt
uliweb/contrib/develop/__init__.py
uliweb/contrib/develop/forms.py
uliweb/contrib/develop/info.ini
uliweb/contrib/develop/menu.py
uliweb/contrib/develop/settings.ini
uliweb/contrib/develop/views.py
uliweb/contrib/develop/templates/develop_appsinfo.html
uliweb/contrib/develop/templates/develop_globals.html
uliweb/contrib/develop/templates/develop_index.html
uliweb/contrib/develop/templates/develop_layout.html
uliweb/contrib/develop/templates/develop_urls.html
uliweb/contrib/eureka/__init__.py
uliweb/contrib/eureka/settings.ini
uliweb/contrib/flashmessage/__init__.py
uliweb/contrib/flashmessage/conf.py
uliweb/contrib/flashmessage/config.ini
uliweb/contrib/flashmessage/info.ini
uliweb/contrib/flashmessage/settings.ini
Uliweb3-0.3.2.dist-info/AUTHORS.md
Uliweb3-0.3.2.dist-info/LICENSE
Uliweb3-0.3.2.dist-info/METADATA
Uliweb3-0.3.2.dist-info/WHEEL
Uliweb3-0.3.2.dist-info/entry_points.txt
Uliweb3-0.3.2.dist-info/top_level.txt
Uliweb3-0.3.2.dist-info/RECORD
