Metadata-Version: 2.1
Name: Uliweb3
Version: 0.3.2
Summary: Easy python web framework
Home-page: https://github.com/limodou/uliweb3
Author: limodou
Author-email: limodou@gmail.com
License: BSD
Keywords: wsgi web framework
Platform: any
Classifier: Development Status :: 5 - Production/Stable
Classifier: Environment :: Console
Classifier: Environment :: Web Environment
Classifier: Intended Audience :: Developers
Classifier: License :: OSI Approved :: BSD License
Classifier: Topic :: Internet :: WWW/HTTP :: WSGI
Classifier: Programming Language :: Python
Classifier: Operating System :: OS Independent
Classifier: Programming Language :: Python :: 3.6
Requires-Dist: pendulum (<3.0)
Requires-Dist: six
Requires-Dist: werkzeug
Requires-Dist: ua-parser
